lavague/contexts/cache/__init__.py
lavague/contexts/cache/base.py
lavague/contexts/cache/embedding_cache.py
lavague/contexts/cache/llm_cache.py
lavague/contexts/cache/mm_llm_cache.py
lavague/contexts/cache/prompts_store.py
lavague_contexts_cache-0.0.1.dist-info/METADATA
lavague_contexts_cache-0.0.1.dist-info/WHEEL
lavague_contexts_cache-0.0.1.dist-info/RECORD
